pygetpapers/__init__.py
pygetpapers/config.ini
pygetpapers/download_tools.py
pygetpapers/pgexceptions.py
pygetpapers/pygetpapers.py
pygetpapers/repositoryinterface.py
pygetpapers/__pycache__/__init__.cpython-37.pyc
pygetpapers/__pycache__/__init__.cpython-38.pyc
pygetpapers/__pycache__/__init__.cpython-39.pyc
pygetpapers/__pycache__/abc.cpython-37.pyc
pygetpapers/__pycache__/demo.cpython-37.pyc
pygetpapers/__pycache__/download_tools.cpython-37.pyc
pygetpapers/__pycache__/download_tools.cpython-38.pyc
pygetpapers/__pycache__/download_tools.cpython-39.pyc
pygetpapers/__pycache__/log_formatter.cpython-37.pyc
pygetpapers/__pycache__/pgexceptions.cpython-37.pyc
pygetpapers/__pycache__/pgexceptions.cpython-38.pyc
pygetpapers/__pycache__/pygetpapers.cpython-37.pyc
pygetpapers/__pycache__/pygetpapers.cpython-38.pyc
pygetpapers/__pycache__/pygetpapers_exceptions.cpython-37.pyc
pygetpapers/__pycache__/repositoryinterface.cpython-37.pyc
pygetpapers/repository/__init__.py
pygetpapers/repository/arxiv.py
pygetpapers/repository/crossref.py
pygetpapers/repository/europe_pmc.py
pygetpapers/repository/rxiv.py
pygetpapers/repository/rxivist.py
pygetpapers/repository/__pycache__/__init__.cpython-37.pyc
pygetpapers/repository/__pycache__/arxiv.cpython-37.pyc
pygetpapers/repository/__pycache__/crossref.cpython-37.pyc
pygetpapers/repository/__pycache__/europe_pmc.cpython-37.pyc
pygetpapers/repository/__pycache__/rxiv.cpython-37.pyc
pygetpapers/repository/__pycache__/rxivist.cpython-37.pyc
pygetpapers-1.2.5.dist-info/LICENSE
pygetpapers-1.2.5.dist-info/METADATA
pygetpapers-1.2.5.dist-info/WHEEL
pygetpapers-1.2.5.dist-info/entry_points.txt
pygetpapers-1.2.5.dist-info/top_level.txt
pygetpapers-1.2.5.dist-info/RECORD
